{"stats":{"minecraft:picked_up":{"minecraft:rotten_flesh":3,"minecraft:dirt":24},"minecraft:custom":{"minecraft:time_since_rest":840008,"minecraft:walk_one_cm":7852,"minecraft:leave_game":3,"minecraft:play_time":926700,"minecraft:damage_taken":13709,"minecraft:time_since_death":840007,"minecraft:deaths":54,"minecraft:total_world_time":926700,"minecraft:fly_one_cm":852,"minecraft:fall_one_cm":525},"minecraft:killed_by":{"minecraft:zombie":43,"minecraft:skeleton":6,"minecraft:creeper":3,"minecraft:spider":2}},"DataVersion":4189}